HarmonyScope/__init__.py
HarmonyScope/analyzer/__init__.py
HarmonyScope/analyzer/chord_analyzer.py
HarmonyScope/cli/common_args.py
HarmonyScope/cli/file_analyze.py
HarmonyScope/cli/mic_analyze.py
HarmonyScope/core/__init__.py
HarmonyScope/core/chord.py
HarmonyScope/core/constants.py
HarmonyScope/core/pitch.py
HarmonyScope/generate.py
HarmonyScope/io/__init__.py
HarmonyScope/io/base.py
HarmonyScope/io/file_reader.py
HarmonyScope/io/mic_reader.py
HarmonyScope/plot_features.py
HarmonyScope/prep/file_frames.py
HarmonyScope/ui/gradio_viewer.py
HarmonyScope/ui/plot.py
HarmonyScope/ui/rich_live.py
HarmonyScope/ui/table.py
harmonyscope-1.0.0.dist-info/METADATA
harmonyscope-1.0.0.dist-info/WHEEL
harmonyscope-1.0.0.dist-info/entry_points.txt
harmonyscope-1.0.0.dist-info/RECORD
