Metadata-Version: 2.3
Name: harmonyscope
Version: 1.0.0
Summary: A real-time and offline chord recognition tool for audio analysis.
License: MIT
Keywords: harmony,chord recognition,audio analysis,real-time,music
Author: as6325400
Author-email: as6325400@gmail.com
Requires-Python: >=3.10,<3.12
Classifier: Development Status :: 3 - Alpha
Classifier: License :: OSI Approved :: MIT License
Classifier: Operating System :: OS Independent
Classifier: Programming Language :: Python :: 3
Classifier: Programming Language :: Python :: 3.10
Classifier: Programming Language :: Python :: 3.11
Classifier: Programming Language :: Python :: 3.8
Classifier: Programming Language :: Python :: 3.9
Requires-Dist: gradio (>=5.33.1,<6.0.0)
Requires-Dist: joblib (>=1.5.1,<2.0.0)
Requires-Dist: librosa (>=0.11.0,<0.12.0)
Requires-Dist: matplotlib (>=3.10.1,<4.0.0)
Requires-Dist: pandas (>=2.3.0,<3.0.0)
Requires-Dist: questionary (>=2.1.0,<3.0.0)
Requires-Dist: rich (>=14.0.0,<15.0.0)
Requires-Dist: sounddevice (>=0.5.1,<0.6.0)
Requires-Dist: tqdm (>=4.67.1,<5.0.0)
Project-URL: Documentation, https://github.com/as6325400/HarmonyScope
Project-URL: Homepage, https://github.com/as6325400/HarmonyScope
Project-URL: Repository, https://github.com/as6325400/HarmonyScope
